{
  "image": "IMG-20251003-WA0085.jpg",
  "image_path": "Products\\IMG-20251003-WA0085.jpg",
  "thumb": "thumbs\\IMG-20251003-WA0085.jpg",
  "article": "jas",
  "colour": "jas",
  "size": "jas",
  "pair": "jas",
  "name": "jas",
  "description": "Art-Rocks 8 Col-White \\ Size-6/9-7/10 ; A™ r Pair 24 a 4 ittTox es es O% At, f iffo | A Leap to sees, | Ge ci",
  "raw_text": "Art-Rocks 8\nCol-White\n\\ Size-6/9-7/10\n; A™ r Pair 24\na 4 ittTox\nY : JAS comfort\nes es O% At, f\niffo |\nA Leap to sees, | Ge ci\n"
}